<?xml version="1.0" encoding="UTF-8"?><findAlumni><DataAlumni id="0"><Nama>Administrator</Nama><YearsOfGrad>S1</YearsOfGrad><Deskripsi>---</Deskripsi><Alamat>Administrator</Alamat><Kebangsaan>---</Kebangsaan><Email>---</Email><Jurusan>---</Jurusan><Tingkat>---</Tingkat><Username>0adminfA</Username><Password>admin</Password><Kemampuan/><Perusahaan/></DataAlumni><DataAlumni id="1"><Nama>aaa</Nama><YearsOfGrad>aaa</YearsOfGrad><Deskripsi>aaa</Deskripsi><Alamat>aaa</Alamat><Kebangsaan>aa</Kebangsaan><Email>aaa</Email><Jurusan>aaa</Jurusan><Tingkat>S1</Tingkat><Username>aaaa</Username><Password>aaaa</Password><Kemampuan><JenisKemampuan idK="0">aaa</JenisKemampuan></Kemampuan><Perusahaan><NamaPerusahaan idP="0">aaaa<NamaJabatan idJ="0">aaaa</NamaJabatan></NamaPerusahaan></Perusahaan></DataAlumni></findAlumni>